__init__.py
lynt.py
user.py
utils/headers.py
utils/logger.py
utils/sse_message.py
lyntrpy-1.0.0.dist-info/LICENSE
lyntrpy-1.0.0.dist-info/METADATA
lyntrpy-1.0.0.dist-info/WHEEL
lyntrpy-1.0.0.dist-info/top_level.txt
lyntrpy-1.0.0.dist-info/RECORD
