Metadata-Version: 2.1
Name: lyntrpy
Version: 1.0.0
Summary: A api wrapper for lyntr`s api in python
Author-email: PlOszukiwacz <ploszukiwacz1@gmail.com>
Project-URL: Homepage, https://github.com/PlOszukiwaczDEV/lyntrpy
Project-URL: Issues, https://github.com/PlOszukiwaczDEV/lyntrpy/issues
Requires-Python: >=3.8
License-File: LICENSE
Requires-Dist: python-dotenv
Requires-Dist: requests
